flowdock.py
flowdock_api_wrapper-1.1.dist-info/LICENSE
flowdock_api_wrapper-1.1.dist-info/WHEEL
flowdock_api_wrapper-1.1.dist-info/METADATA
flowdock_api_wrapper-1.1.dist-info/RECORD
