Metadata-Version: 2.1
Name: flowdock-api-wrapper
Version: 1.1
Summary: Flowdock API Wrapper
Keywords: flowdock
Requires-Python: >=3.6
Classifier: Development Status :: 5 - Production/Stable
Classifier: Intended Audience :: Developers
Classifier: Intended Audience :: System Administrators
Classifier: License :: OSI Approved :: MIT License
Classifier: Natural Language :: English
Classifier: Operating System :: OS Independent
Classifier: Programming Language :: Python :: 3 :: Only
Classifier: Programming Language :: Python :: 3.6
Classifier: Programming Language :: Python :: 3.7
Classifier: Programming Language :: Python :: 3.8
Classifier: Programming Language :: Python :: 3.9
Classifier: Topic :: Communications :: Chat
Classifier: Topic :: Communications :: Conferencing
Requires-Dist: requests
Project-URL: Source, https://github.com/apua/flowdock
